{
  "descriptionHash": "7C0A93C7E6DFDC450D3037E6B84E0ABA732D49C23401ECD78EA2A08446669AABB06FB34912F6CECB30D1D34B5F619EC2CC1C1CEBA5A3FB7F9DEF520F453A7A53",
  "descriptionLocation": "https://dataset.api.hub.geosphere.at/v1/openapi.json",
  "lockFileVersion": "1.0.0",
  "kiotaVersion": "1.21.0",
  "clientClassName": "GeoSphereApiClient",
  "typeAccessModifier": "Public",
  "clientNamespaceName": "ApiSdk",
  "language": "CSharp",
  "usesBackingStore": false,
  "excludeBackwardCompatible": false,
  "includeAdditionalData": true,
  "disableSSLValidation": false,
  "serializers": [
    "Microsoft.Kiota.Serialization.Json.JsonSerializationWriterFactory",
    "Microsoft.Kiota.Serialization.Text.TextSerializationWriterFactory",
    "Microsoft.Kiota.Serialization.Form.FormSerializationWriterFactory",
    "Microsoft.Kiota.Serialization.Multipart.MultipartSerializationWriterFactory"
  ],
  "deserializers": [
    "Microsoft.Kiota.Serialization.Json.JsonParseNodeFactory",
    "Microsoft.Kiota.Serialization.Text.TextParseNodeFactory",
    "Microsoft.Kiota.Serialization.Form.FormParseNodeFactory"
  ],
  "structuredMimeTypes": [
    "application/json",
    "text/plain;q=0.9",
    "application/x-www-form-urlencoded;q=0.2",
    "multipart/form-data;q=0.1"
  ],
  "includePatterns": [],
  "excludePatterns": [],
  "disabledValidationRules": []
}